<?xml version='1.0' encoding='UTF-8'?>
<faces-config version="2.2" xmlns="http://xmlns.jcp.org/xml/ns/javaee"
              xmlns:xsi="http://www.w3.org/2001/XMLSchema-instance"
              xsi:schemaLocation="http://xmlns.jcp.org/xml/ns/javaee 
	http://xmlns.jcp.org/xml/ns/javaee/web-facesconfig_2_2.xsd">

    <welcome-file-list>
        <welcome-file>login.xhtml</welcome-file>
    </welcome-file-list>
        
    <filter>
        <filter-name>AuthorizationFilter</filter-name>
        <filter-class>filter.AuthorizationFilter</filter-class>
    </filter>
    <filter-mapping>
        <filter-name>AuthorizationFilter</filter-name>
        <url-pattern>/secured/*</url-pattern>
    </filter-mapping>

</faces-config>
